CHANGES.rst
DESCRIPTION.rst
LICENSE
MANIFEST.in
README.md
setup.py
src/idc/plantcv/__init__.py
src/idc/plantcv/class_lister.py
src/idc/plantcv/filter/__init__.py
src/idc/plantcv/filter/_dilate.py
src/idc/plantcv/filter/_erode.py
src/idc/plantcv/filter/_fill.py
src/idc/plantcv/filter/_fill_holes.py
src/idc/plantcv/filter/_find_branch_points.py
src/idc/plantcv/filter/_find_tips.py
src/idc/plantcv/filter/_morphological_filter.py
src/idc/plantcv/filter/_skeletonize.py
src/image_dataset_converter_plantcv.egg-info/PKG-INFO
src/image_dataset_converter_plantcv.egg-info/SOURCES.txt
src/image_dataset_converter_plantcv.egg-info/dependency_links.txt
src/image_dataset_converter_plantcv.egg-info/entry_points.txt
src/image_dataset_converter_plantcv.egg-info/requires.txt
src/image_dataset_converter_plantcv.egg-info/top_level.txt