Metadata-Version: 2.1
Name: image-dataset-converter-plantcv
Version: 0.0.1
Summary: image-dataset-converter plugins for plantcv (https://github.com/danforthcenter/plantcv).
Home-page: https://github.com/waikato-datamining/image-dataset-converter-plantcv
Author: Peter Reutemann
Author-email: fracpete@waikato.ac.nz
License: MIT License
Classifier: Development Status :: 4 - Beta
Classifier: License :: OSI Approved :: MIT License
Classifier: Topic :: Scientific/Engineering :: Artificial Intelligence
Classifier: Topic :: Scientific/Engineering :: Image Processing
License-File: LICENSE
